digitalization/__init__.py
digitalization-0.1.3.dist-info/LICENSE
digitalization-0.1.3.dist-info/METADATA
digitalization-0.1.3.dist-info/WHEEL
digitalization-0.1.3.dist-info/top_level.txt
digitalization-0.1.3.dist-info/RECORD
