Metadata-Version: 2.1
Name: digitalization
Version: 0.1.3
Summary: A test package for ops automation
Home-page: https://github.com/thangnt/digitalization
Author: thangnt
Author-email: mr.thangnt@gmail.com
Classifier: Programming Language :: Python :: 3
Classifier: License :: OSI Approved :: MIT License
Classifier: Operating System :: OS Independent
Requires-Python: >=3.7
License-File: LICENSE
